outersum/__init__.py
outersum/core.py
outersum/utils.py
tests/__init__.py
tests/test_core.py
outersum-0.1.0.dist-info/LICENSE
outersum-0.1.0.dist-info/METADATA
outersum-0.1.0.dist-info/WHEEL
outersum-0.1.0.dist-info/top_level.txt
outersum-0.1.0.dist-info/RECORD
